[
  {
    "id": 1727862253827,
    "title": "Hí anh em",
    "content": "<p>Tộc Chưởng đây.</p>",
    "createAt": "2024-10-02T09:44:13.827Z",
    "username": "duy",
    "status": "public"
  },
  {
    "id": 1728115293338,
    "title": "abcde",
    "content": "<p>heheheee</p>",
    "createAt": "2024-10-05T08:01:33.338Z",
    "username": "duy",
    "status": "public"
  },
  {
    "id": 1728123031187,
    "title": "Alooo",
    "content": "<p>123,1234</p>",
    "createAt": "2024-10-05T10:10:31.187Z",
    "username": "a",
    "status": "public"
  },
  {
    "id": 1728123065551,
    "title": "Cái ni riêng tư nè",
    "content": "<p>hehe</p>",
    "createAt": "2024-10-05T10:11:05.551Z",
    "username": "duy",
    "status": "private"
  }
]